{"parents": [{"link": "../../../", "title": "Finance"}, {"link": "../../", "title": "Guides"}], "prev": {"link": "../taxes/", "title": "Taxes"}, "next": {"link": "../../revenue/bank_accounts/", "title": "Adding a Bank Account"}, "title": "Vendors", "meta": null, "body": "<div class=\"section\" id=\"vendors\">\n<h1>Vendors<a class=\"headerlink\" href=\"#vendors\" title=\"Permalink to this headline\">\u00b6</a></h1>\n<div class=\"line-block\">\n<div class=\"line\"><strong>Vendors</strong> displays a list of all the vendors from which your association has bought items.</div>\n</div>\n<ol class=\"arabic simple\">\n<li><p>Click the <i class=\"fa fa-bars\"></i> in the ribbon</p></li>\n<li><p>Click <strong>Finance</strong></p></li>\n<li><p>Click <strong>Expenses</strong></p></li>\n<li><p>Click <strong>Vendor</strong></p></li>\n<li><p>Click the <i class=\"fa fa-ellipsis-h\"></i> to the right of a row</p></li>\n<li><p>Click <a class=\"reference external\" href=\"/users/finance/guides/how_to_merge.html\">Merge Vendors</a> to merge the vendor with another vendor in the system</p></li>\n<li><p>Click <a class=\"reference external\" href=\"/users/general/guides/functions_of_the_grid/how_to_edit.html\">Edit Vendor</a> to make changes to the vendor</p></li>\n<li><p>Create a <a class=\"reference external\" href=\"/users/finance/guides/expenses/add_a_vendor.html\">New Vendor</a></p></li>\n</ol>\n</div>\n", "metatags": "", "rellinks": [["genindex", "General Index", "I", "index"], ["users/finance/guides/revenue/bank_accounts", "Adding a Bank Account", "N", "next"], ["users/finance/guides/expenses/taxes", "Taxes", "P", "previous"]], "sourcename": "users/finance/guides/expenses/vendor.rst.txt", "toc": "<ul>\n<li><a class=\"reference internal\" href=\"#\">Vendors</a></li>\n</ul>\n", "display_toc": false, "page_source_suffix": ".rst", "current_page_name": "users/finance/guides/expenses/vendor", "sidebars": ["localtoc.html", "relations.html", "sourcelink.html", "searchbox.html"], "customsidebar": null, "favicon_url": null, "logo_url": null, "alabaster_version": "0.7.12"}