{"parents": [], "prev": {"link": "../chat/reference/", "title": "&lt;no title&gt;"}, "next": {"link": "guides/", "title": "&lt;no title&gt;"}, "title": "CRM", "meta": null, "body": "<div class=\"section\" id=\"crm\">\n<h1>CRM<a class=\"headerlink\" href=\"#crm\" title=\"Permalink to this headline\">\u00b6</a></h1>\n<p>The CRM app is a clearinghouse for all of your organization\u2019s contacts. From\ncustomers to colleagues to partners, every person your organization interacts\nwith should have a record in the CRM. The CRM tracks your interactions with\neach contact, creating a institutional memory of each contacts history of\nengagement with your organization.</p>\n<div class=\"toctree-wrapper compound\">\n<ul>\n<li class=\"toctree-l1\"><a class=\"reference internal\" href=\"guides/contacts/add_a_new_contact/\">Adding a New Contact</a></li>\n<li class=\"toctree-l1\"><a class=\"reference internal\" href=\"guides/contacts/add_contact/\">Adding a Contact</a></li>\n<li class=\"toctree-l1\"><a class=\"reference internal\" href=\"guides/contacts/contacts/\">Contacts</a></li>\n<li class=\"toctree-l1\"><a class=\"reference internal\" href=\"guides/contacts/import_contacts/\">Importing Contacts</a></li>\n<li class=\"toctree-l1\"><a class=\"reference internal\" href=\"guides/programs/access/\">Access</a></li>\n<li class=\"toctree-l1\"><a class=\"reference internal\" href=\"guides/programs/add_a_new_program/\">Add a New Program</a></li>\n<li class=\"toctree-l1\"><a class=\"reference internal\" href=\"guides/programs/details/\">Details</a></li>\n<li class=\"toctree-l1\"><a class=\"reference internal\" href=\"guides/programs/lists/\">Lists</a></li>\n<li class=\"toctree-l1\"><a class=\"reference internal\" href=\"guides/programs/programs/\">Programs</a></li>\n<li class=\"toctree-l1\"><a class=\"reference internal\" href=\"guides/programs/properties/\">Properties</a></li>\n<li class=\"toctree-l1\"><a class=\"reference internal\" href=\"guides/programs/senders/\">Senders</a></li>\n<li class=\"toctree-l1\"><a class=\"reference internal\" href=\"guides/programs/templates/\">Templates</a></li>\n<li class=\"toctree-l1\"><a class=\"reference internal\" href=\"guides/programs/topics/\">Topics</a></li>\n</ul>\n</div>\n</div>\n", "metatags": "", "rellinks": [["genindex", "General Index", "I", "index"], ["users/crm/guides/index", "&lt;no title&gt;", "N", "next"], ["users/chat/reference", "&lt;no title&gt;", "P", "previous"]], "sourcename": "users/crm/index.rst.txt", "toc": "<ul>\n<li><a class=\"reference internal\" href=\"#\">CRM</a></li>\n</ul>\n", "display_toc": false, "page_source_suffix": ".rst", "current_page_name": "users/crm/index", "sidebars": ["localtoc.html", "relations.html", "sourcelink.html", "searchbox.html"], "customsidebar": null, "favicon_url": null, "logo_url": null, "alabaster_version": "0.7.12"}