{"parents": [{"link": "../../", "title": "Websites"}], "prev": {"link": "../redirects/", "title": "&lt;no title&gt;"}, "next": {"link": "../theme/", "title": "&lt;no title&gt;"}, "title": "&lt;no title&gt;", "meta": null, "body": "<p>Websites:</p>\n<div class=\"line-block\">\n<div class=\"line\"><br /></div>\n<div class=\"line\">To view the details of a website, you will need to have navigated to the website. Refer <a class=\"reference external\" href=\"/users/websites/guides/websites.html\">here</a> if you are having trouble reaching this point.</div>\n</div>\n<ol class=\"arabic simple\">\n<li><p>Click <i class=\"fa fa-files-o\"></i> <strong>Templates</strong></p></li>\n<li><p>Click <i class=\"fa fa-plus\"></i> in the upper right hand corner</p></li>\n<li><p>Enter a title</p></li>\n<li><p>Click <strong>Save</strong></p></li>\n</ol>\n", "metatags": "", "rellinks": [["genindex", "General Index", "I", "index"], ["users/websites/guides/theme", "&lt;no title&gt;", "N", "next"], ["users/websites/guides/redirects", "&lt;no title&gt;", "P", "previous"]], "sourcename": "users/websites/guides/templates.rst.txt", "toc": "<ul class=\"simple\">\n</ul>\n", "display_toc": false, "page_source_suffix": ".rst", "current_page_name": "users/websites/guides/templates", "sidebars": ["localtoc.html", "relations.html", "sourcelink.html", "searchbox.html"], "customsidebar": null, "favicon_url": null, "logo_url": null, "alabaster_version": "0.7.12"}